regression_model/VERSION
regression_model/__init__.py
regression_model/config.yml
regression_model/pipeline.py
regression_model/predict.py
regression_model/train_pipeline.py
regression_model/config/__init__.py
regression_model/config/core.py
regression_model/datasets/__init__.py
regression_model/datasets/test.csv
regression_model/datasets/train.csv
regression_model/processing/__init__.py
regression_model/processing/data_manager.py
regression_model/processing/features.py
regression_model/processing/validation.py
regression_model/trained_models/__init__.py
regression_model/trained_models/regression_model_output_v2.1.1.pkl
model_regresi_harga_rumah-2.1.1.dist-info/METADATA
model_regresi_harga_rumah-2.1.1.dist-info/WHEEL
model_regresi_harga_rumah-2.1.1.dist-info/top_level.txt
model_regresi_harga_rumah-2.1.1.dist-info/RECORD
